photini/__init__.py
photini/__main__.py
photini/_version.py
photini/address.py
photini/azuremap.py
photini/configstore.py
photini/cv.py
photini/descriptive.py
photini/editor.py
photini/editsettings.py
photini/exiv2.py
photini/ffmpeg.py
photini/flickr.py
photini/googlemap.py
photini/googlephotos.py
photini/gpximporter.py
photini/imagelist.py
photini/importer.py
photini/ipernity.py
photini/keywords.py
photini/linux.py
photini/loggerwindow.py
photini/macos.py
photini/mapboxmap.py
photini/metadata.py
photini/ownership.py
photini/photinimap.py
photini/pixelfed.py
photini/pyqt.py
photini/regions.py
photini/scripts.py
photini/spelling.py
photini/technical.py
photini/types.py
photini/uploader.py
photini/vocab.py
photini/widgets.py
photini/windows.py
photini/data/LICENSE.txt
photini/data/keys.txt
photini/data/icons/photini.icns
photini/data/icons/photini_win.ico
photini/data/icons/linux/128x128/photini.png
photini/data/icons/linux/16x16/photini.png
photini/data/icons/linux/24x24/photini.png
photini/data/icons/linux/256x256/photini.png
photini/data/icons/linux/32x32/photini.png
photini/data/icons/linux/48x48/photini.png
photini/data/icons/linux/64x64/photini.png
photini/data/lang/photini.ca.qm
photini/data/lang/photini.cs.qm
photini/data/lang/photini.de.qm
photini/data/lang/photini.en.qm
photini/data/lang/photini.es.qm
photini/data/lang/photini.fr.qm
photini/data/lang/photini.it.qm
photini/data/lang/photini.ko.qm
photini/data/lang/photini.nb.qm
photini/data/lang/photini.pl.qm
photini/data/lang/photini.ta.qm
photini/data/map/azuremap.js
photini/data/map/googlemap.js
photini/data/map/mapboxmap.js
photini/data/map/mapboxmap_legacy.js
photini/data/map/pin_alpha.png
photini/data/map/pin_image.png
photini-2025.10.0.dist-info/licenses/LICENSE.txt
photini-2025.10.0.dist-info/METADATA
photini-2025.10.0.dist-info/WHEEL
photini-2025.10.0.dist-info/entry_points.txt
photini-2025.10.0.dist-info/top_level.txt
photini-2025.10.0.dist-info/RECORD
