Metadata-Version: 2.4
Name: Photini
Version: 2025.10.0
Summary: Simple photo metadata editor
Author-email: Jim Easterbrook <jim@jim-easterbrook.me.uk>
License: GPLv3+
Project-URL: Homepage, https://github.com/jim-easterbrook/Photini
Project-URL: Documentation, https://photini.readthedocs.io/
Project-URL: Repository, https://github.com/jim-easterbrook/Photini
Project-URL: Changelog, https://github.com/jim-easterbrook/Photini/blob/main/CHANGELOG.txt
Keywords: Exif,IPTC,XMP
Classifier: Development Status :: 5 - Production/Stable
Classifier: Environment :: Win32 (MS Windows)
Classifier: Environment :: X11 Applications :: Qt
Classifier: Intended Audience :: End Users/Desktop
Classifier: License :: OSI Approved :: GNU General Public License v3 or later (GPLv3+)
Classifier: Operating System :: OS Independent
Classifier: Programming Language :: Python :: 3
Classifier: Topic :: Multimedia :: Graphics
Requires-Python: >=3.6
License-File: LICENSE.txt
Requires-Dist: cachetools>=3.0
Requires-Dist: chardet>=3.0
Requires-Dist: exiv2>=0.16
Requires-Dist: filetype>=1.0
Requires-Dist: Pillow>=5.3
Requires-Dist: platformdirs>=2.4
Requires-Dist: requests>=2.4
Requires-Dist: pywin32>=302; platform_system == "Windows"
Provides-Extra: flickr
Requires-Dist: photini[keyring,requests-oauthlib,requests-toolbelt]; extra == "flickr"
Provides-Extra: google
Requires-Dist: photini[keyring,requests-oauthlib]; extra == "google"
Provides-Extra: importer
Requires-Dist: gphoto2>=2.4; platform_system != "Windows" and extra == "importer"
Provides-Extra: ipernity
Requires-Dist: photini[keyring,requests-toolbelt]; extra == "ipernity"
Provides-Extra: pixelfed
Requires-Dist: photini[keyring,requests-oauthlib,requests-toolbelt]; extra == "pixelfed"
Provides-Extra: spelling
Requires-Dist: pyenchant>=2.0; extra == "spelling"
Provides-Extra: all
Requires-Dist: photini[gpxpy,importer,keyring,requests-oauthlib,requests-toolbelt,spelling]; extra == "all"
Provides-Extra: keyring
Requires-Dist: keyring>=7.0; extra == "keyring"
Provides-Extra: requests-oauthlib
Requires-Dist: requests-oauthlib>=1.0; extra == "requests-oauthlib"
Provides-Extra: requests-toolbelt
Requires-Dist: requests-toolbelt>=0.9; extra == "requests-toolbelt"
Provides-Extra: pyqt5
Requires-Dist: PyQt5>=5.9; extra == "pyqt5"
Requires-Dist: PyQtWebEngine>=5.12; extra == "pyqt5"
Provides-Extra: pyqt6
Requires-Dist: photini[PyQt6-linux]; platform_system == "Linux" and extra == "pyqt6"
Requires-Dist: photini[PyQt6-windows]; platform_system == "Windows" and extra == "pyqt6"
Requires-Dist: photini[PyQt6-darwin]; platform_system == "Darwin" and extra == "pyqt6"
Provides-Extra: pyqt6-linux
Requires-Dist: PyQt6>=6.2; python_version != "3.6.*" and extra == "pyqt6-linux"
Requires-Dist: PyQt6-WebEngine>=6.2; python_version != "3.6.*" and extra == "pyqt6-linux"
Requires-Dist: PyQt6<6.3,>=6.2; python_version == "3.6.*" and extra == "pyqt6-linux"
Requires-Dist: PyQt6-Qt6<6.3; python_version == "3.6.*" and extra == "pyqt6-linux"
Requires-Dist: PyQt6-WebEngine<6.3,>=6.2; python_version == "3.6.*" and extra == "pyqt6-linux"
Requires-Dist: PyQt6-WebEngine-Qt6<6.3; python_version == "3.6.*" and extra == "pyqt6-linux"
Provides-Extra: pyqt6-windows
Requires-Dist: PyQt6>=6.2; platform_release not in "7" and extra == "pyqt6-windows"
Requires-Dist: PyQt6-WebEngine>=6.2; platform_release not in "7" and extra == "pyqt6-windows"
Requires-Dist: Qt6-unavailable; platform_release in "7" and extra == "pyqt6-windows"
Provides-Extra: pyqt6-darwin
Requires-Dist: PyQt6-Qt6!=6.6.1,>=6.2; extra == "pyqt6-darwin"
Requires-Dist: PyQt6-WebEngine-Qt6!=6.6.1,>=6.2; extra == "pyqt6-darwin"
Provides-Extra: pyside2
Requires-Dist: PySide2>=5.11.1; python_version < "3.8" and extra == "pyside2"
Requires-Dist: PySide2>=5.14; python_version >= "3.8" and extra == "pyside2"
Provides-Extra: pyside6
Requires-Dist: photini[PySide6-linux]; platform_system == "Linux" and extra == "pyside6"
Requires-Dist: photini[PySide6-windows]; platform_system == "Windows" and extra == "pyside6"
Requires-Dist: photini[PySide6-darwin]; platform_system == "Darwin" and extra == "pyside6"
Provides-Extra: pyside6-linux
Requires-Dist: PySide6>=6.2; extra == "pyside6-linux"
Provides-Extra: pyside6-windows
Requires-Dist: PySide6>=6.2; platform_release not in "7" and extra == "pyside6-windows"
Requires-Dist: Qt6-unavailable; platform_release in "7" and extra == "pyside6-windows"
Provides-Extra: pyside6-darwin
Requires-Dist: PySide6!=6.6.1,>=6.2; extra == "pyside6-darwin"
Provides-Extra: gpxpy
Requires-Dist: gpxpy!=1.6.0,>=1.3.5; extra == "gpxpy"
Provides-Extra: pillow
Dynamic: license-file
